Metadata-Version: 2.1
Name: oneNeuron-pypi-Jateendra
Version: 0.0.2
Summary: It is an implementation of Perceptron
Home-page: https://github.com/Jateendra/oneNeuron_pypi
Author: Jateendra
Author-email: mypython.pradhan@gmail.com
License: UNKNOWN
Project-URL: Bug Tracker, https://github.com/Jateendra/oneNeuron_pypi/issues
Platform: UNKNOWN
Classifier: Programming Language :: Python :: 3
Classifier: License :: OSI Approved :: MIT License
Classifier: Operating System :: OS Independent
Requires-Python: >=3.7
License-File: LICENSE
Requires-Dist: numpy
Requires-Dist: tqdm
